{
  "ModsLabs_DeviceAuth": [
    {
      "id": "3de73558456d0e5a",
      "name": "Admin Reddy"
    },
    {
      "id": "bfad7f87761b90b1",
      "name": "Kholil"
    },
    {
      "id": "c11e2b6ac2424b0f",
      "name": "Naeim"
    },
    {
      "id": "ABCDEF123456",
      "name": "Test Phone"
    },
    {
      "id": "ABCDEF123456",
      "name": "Test Phone"
    },
    {
      "id": "ABCDEF123456",
      "name": "Test Phone"
    },
    {
      "id": "ABCDEF123456",
      "name": "Test Phone"
    },
    {
      "id": "ABCDEF123456",
      "name": "Test Phone"
    },
    {
      "id": "ABCDEF123456",
      "name": "Test Phone"
    },
    {
      "id": "ABCDEF123456",
      "name": "Test Phone"
    },
    {
      "id": "ABCDEF123456",
      "name": "Test Phone"
    },
    {
      "id": "ABCDEF123456",
      "name": "Test Phone"
    }
  ]
}
